waykit/__init__.py
waykit/models.py
waykit/openstreetmap_provider.py
waykit-0.1.0.dist-info/WHEEL
waykit-0.1.0.dist-info/entry_points.txt
waykit-0.1.0.dist-info/METADATA
waykit-0.1.0.dist-info/RECORD
