Metadata-Version: 2.3
Name: waykit
Version: 0.1.0
Summary: generate location metatata like peaks, huts for a given gpx file
Author: Peter Hoffmann
Author-email: Peter Hoffmann <ph@peter-hoffmann.com>
Requires-Dist: gpxpy>=1.6.2
Requires-Dist: pydantic>=2.12.4
Requires-Dist: requests>=2.32.5
Requires-Python: >=3.13
